imfusion/Algorithm.py
imfusion/ImFusionVisualizer
imfusion/__init__.py
imfusion/_bindings.cpython-310-darwin.so
imfusion/dicom.cpython-310-darwin.so
imfusion/imagemath.cpython-310-darwin.so
imfusion/registration.cpython-310-darwin.so
imfusion/acknowledgments/Acknowledgments.txt
imfusion/acknowledgments/AcknowledgmentsModels.txt
imfusion/labels/__init__.py
imfusion/labels/_bindings.cpython-310-darwin.so
imfusion/lib/lib3mf.2.dylib
imfusion/lib/libAnnotationLib.dylib
imfusion/lib/libImFusionCore.dylib
imfusion/lib/libImFusionGL.dylib
imfusion/lib/libImFusionLib.dylib
imfusion/lib/libImFusionPythonHelpers.dylib
imfusion/lib/libboost_atomic-mt.dylib
imfusion/lib/libboost_chrono-mt.dylib
imfusion/lib/libboost_date_time-mt.dylib
imfusion/lib/libboost_filesystem-mt.dylib
imfusion/lib/libboost_iostreams-mt.dylib
imfusion/lib/libboost_locale-mt.dylib
imfusion/lib/libboost_program_options-mt.dylib
imfusion/lib/libboost_regex-mt.dylib
imfusion/lib/libboost_system-mt.dylib
imfusion/lib/libboost_thread-mt.dylib
imfusion/lib/libcpr.1.dylib
imfusion/lib/libflann.1.9.dylib
imfusion/lib/libflann_cpp.1.9.dylib
imfusion/lib/libfreetype.6.dylib
imfusion/lib/libglib-2.0.0.dylib
imfusion/lib/libgthread-2.0.0.dylib
imfusion/lib/libhdf5.103.dylib
imfusion/lib/libhdf5_cpp.103.dylib
imfusion/lib/libhdf5_hl.100.dylib
imfusion/lib/libhdf5_hl_cpp.100.dylib
imfusion/lib/libicudata.73.dylib
imfusion/lib/libicui18n.73.dylib
imfusion/lib/libicuuc.73.dylib
imfusion/lib/libintl.8.dylib
imfusion/lib/libjpeg.8.dylib
imfusion/lib/liblz4.1.dylib
imfusion/lib/liblzma.5.dylib
imfusion/lib/libnlopt.0.dylib
imfusion/lib/libomp.dylib
imfusion/lib/libpcl_common.1.13.dylib
imfusion/lib/libpcl_features.1.13.dylib
imfusion/lib/libpcl_filters.1.13.dylib
imfusion/lib/libpcl_io.1.13.dylib
imfusion/lib/libpcl_io_ply.1.13.dylib
imfusion/lib/libpcl_kdtree.1.13.dylib
imfusion/lib/libpcl_keypoints.1.13.dylib
imfusion/lib/libpcl_ml.1.13.dylib
imfusion/lib/libpcl_octree.1.13.dylib
imfusion_sdk-0.10.0.dist-info/licenses/LICENSE
imfusion_sdk-0.10.0.dist-info/METADATA
imfusion_sdk-0.10.0.dist-info/WHEEL
imfusion_sdk-0.10.0.dist-info/top_level.txt
imfusion_sdk-0.10.0.dist-info/RECORD
