Metadata-Version: 2.4
Name: imfusion-sdk
Version: 0.10.0
Summary: ImFusion - Enabling Rapid Innovation in Medical Imaging
Author-email: ImFusion GmbH <python@imfusion.com>, Markus Habert <habert@imfusion.com>, Ilja Manakov <manakov@imfusion.com>
License-Expression: LicenseRef-ImFusion-EULA
Project-URL: Homepage, https://www.imfusion.com
Project-URL: Documentation, https://docs.imfusion.com/python
Project-URL: Forum, https://forum.imfusion.com/c/python-sdk
Project-URL: Webshop, https://shop.imfusion.com
Keywords: ImFusion,Medical Imaging,Image Processing,Image Manipulation,Hardware Acceleration,GPU Acceleration,SDK
Classifier: Programming Language :: Python :: 3
Classifier: Programming Language :: Python :: 3.9
Classifier: Programming Language :: Python :: 3.10
Classifier: Programming Language :: Python :: 3.11
Classifier: Programming Language :: Python :: 3.12
Classifier: Intended Audience :: Science/Research
Classifier: Intended Audience :: Healthcare Industry
Classifier: Topic :: Scientific/Engineering :: Image Processing
Classifier: Topic :: Scientific/Engineering :: Medical Science Apps.
Classifier: Operating System :: OS Independent
Classifier: Development Status :: 4 - Beta
Classifier: Typing :: Typed
Requires-Python: >=3.9
License-File: LICENSE
Requires-Dist: numpy
Dynamic: license-file
